MANIFEST.in
README.rst
setup.py
jingtum_python_baselib/__init__.py
jingtum_python_baselib/base58.py
jingtum_python_baselib/datacheck.py
jingtum_python_baselib/keypairs.py
jingtum_python_baselib/serializer.py
jingtum_python_baselib/tum_amount.py
jingtum_python_baselib/typesutils.py
jingtum_python_baselib/utils.py
jingtum_python_baselib/wallet.py
jingtum_python_lib/__init__.py
jingtum_python_lib/account.py
jingtum_python_lib/config.json
jingtum_python_lib/config.py
jingtum_python_lib/logger.py
jingtum_python_lib/remote.py
jingtum_python_lib/request.py
jingtum_python_lib/server.py
jingtum_python_lib/transaction.py
jingtum_python_lib/utils.py
jingtum_python_lib.egg-info/PKG-INFO
jingtum_python_lib.egg-info/SOURCES.txt
jingtum_python_lib.egg-info/dependency_links.txt
jingtum_python_lib.egg-info/not-zip-safe
jingtum_python_lib.egg-info/requires.txt
jingtum_python_lib.egg-info/top_level.txt