Metadata-Version: 1.1
Name: jingtum-python-lib
Version: 2.1.0
Summary: jingtum_lib to be used for interacting with jingtum blockchain network
Home-page: https://github.com/swtcpro/jingtum-lib-python
Author: wuhan python dev team
Author-email: caizl2002@hotmail.com
License: MIT
Keywords: jingtum,lib,python
Platform: UNKNOWN
Classifier: Programming Language :: Python :: 3
Classifier: License :: OSI Approved :: MIT License
Classifier: Operating System :: OS Independent
